{
  "id": "e007d235-5e64-4b04-a068-984e1532723d",
  "prevId": "00000000-0000-0000-0000-000000000000",
  "version": "7",
  "dialect": "postgresql",
  "tables": {
    "public.game_catalog": {
      "name": "game_catalog",
      "schema": "",
      "columns": {
        "slug": {
          "name": "slug",
          "type": "varchar(64)",
          "primaryKey": true,
          "notNull": true
        },
        "display_name": {
          "name": "display_name",
          "type": "varchar(128)",
          "primaryKey": false,
          "notNull": true
        },
        "sort_order": {
          "name": "sort_order",
          "type": "integer",
          "primaryKey": false,
          "notNull": true
        },
        "enabled": {
          "name": "enabled",
          "type": "boolean",
          "primaryKey": false,
          "notNull": true
        },
        "released": {
          "name": "released",
          "type": "boolean",
          "primaryKey": false,
          "notNull": true
        }
      },
      "indexes": {},
      "foreignKeys": {},
      "compositePrimaryKeys": {},
      "uniqueConstraints": {},
      "policies": {},
      "checkConstraints": {},
      "isRLSEnabled": false
    },
    "public.game_sessions": {
      "name": "game_sessions",
      "schema": "",
      "columns": {
        "user_id": {
          "name": "user_id",
          "type": "uuid",
          "primaryKey": false,
          "notNull": true
        },
        "game_slug": {
          "name": "game_slug",
          "type": "varchar(64)",
          "primaryKey": false,
          "notNull": true
        },
        "session_data": {
          "name": "session_data",
          "type": "jsonb",
          "primaryKey": false,
          "notNull": true
        },
        "created_at": {
          "name": "created_at",
          "type": "timestamp with time zone",
          "primaryKey": false,
          "notNull": true,
          "default": "now()"
        },
        "updated_at": {
          "name": "updated_at",
          "type": "timestamp with time zone",
          "primaryKey": false,
          "notNull": true,
          "default": "now()"
        }
      },
      "indexes": {},
      "foreignKeys": {},
      "compositePrimaryKeys": {
        "game_sessions_user_id_game_slug_pk": {
          "name": "game_sessions_user_id_game_slug_pk",
          "columns": [
            "user_id",
            "game_slug"
          ]
        }
      },
      "uniqueConstraints": {},
      "policies": {},
      "checkConstraints": {},
      "isRLSEnabled": false
    },
    "public.player_dart_stats": {
      "name": "player_dart_stats",
      "schema": "",
      "columns": {
        "user_id": {
          "name": "user_id",
          "type": "uuid",
          "primaryKey": true,
          "notNull": true
        },
        "double_attempts": {
          "name": "double_attempts",
          "type": "integer",
          "primaryKey": false,
          "notNull": true,
          "default": 0
        },
        "double_hits": {
          "name": "double_hits",
          "type": "integer",
          "primaryKey": false,
          "notNull": true,
          "default": 0
        },
        "total_checkouts": {
          "name": "total_checkouts",
          "type": "integer",
          "primaryKey": false,
          "notNull": true,
          "default": 0
        },
        "total_checkout_darts": {
          "name": "total_checkout_darts",
          "type": "integer",
          "primaryKey": false,
          "notNull": true,
          "default": 0
        }
      },
      "indexes": {},
      "foreignKeys": {},
      "compositePrimaryKeys": {},
      "uniqueConstraints": {},
      "policies": {},
      "checkConstraints": {},
      "isRLSEnabled": false
    },
    "public.player_score_training_stats": {
      "name": "player_score_training_stats",
      "schema": "",
      "columns": {
        "user_id": {
          "name": "user_id",
          "type": "uuid",
          "primaryKey": true,
          "notNull": true
        },
        "games_completed": {
          "name": "games_completed",
          "type": "integer",
          "primaryKey": false,
          "notNull": true,
          "default": 0
        },
        "total_darts_thrown": {
          "name": "total_darts_thrown",
          "type": "integer",
          "primaryKey": false,
          "notNull": true,
          "default": 0
        },
        "total_points_scored": {
          "name": "total_points_scored",
          "type": "integer",
          "primaryKey": false,
          "notNull": true,
          "default": 0
        },
        "best_visit_score": {
          "name": "best_visit_score",
          "type": "integer",
          "primaryKey": false,
          "notNull": true,
          "default": 0
        },
        "best_game_average": {
          "name": "best_game_average",
          "type": "real",
          "primaryKey": false,
          "notNull": true,
          "default": 0
        }
      },
      "indexes": {},
      "foreignKeys": {},
      "compositePrimaryKeys": {},
      "uniqueConstraints": {},
      "policies": {},
      "checkConstraints": {},
      "isRLSEnabled": false
    },
    "public.player_singles_training_stats": {
      "name": "player_singles_training_stats",
      "schema": "",
      "columns": {
        "user_id": {
          "name": "user_id",
          "type": "uuid",
          "primaryKey": true,
          "notNull": true
        },
        "games_completed": {
          "name": "games_completed",
          "type": "integer",
          "primaryKey": false,
          "notNull": true,
          "default": 0
        },
        "games_failed": {
          "name": "games_failed",
          "type": "integer",
          "primaryKey": false,
          "notNull": true,
          "default": 0
        },
        "total_darts_thrown": {
          "name": "total_darts_thrown",
          "type": "integer",
          "primaryKey": false,
          "notNull": true,
          "default": 0
        },
        "total_hits": {
          "name": "total_hits",
          "type": "integer",
          "primaryKey": false,
          "notNull": true,
          "default": 0
        },
        "total_score": {
          "name": "total_score",
          "type": "integer",
          "primaryKey": false,
          "notNull": true,
          "default": 0
        },
        "dart_position_hits": {
          "name": "dart_position_hits",
          "type": "integer[]",
          "primaryKey": false,
          "notNull": true,
          "default": "'{0,0,0}'"
        },
        "dart_position_attempts": {
          "name": "dart_position_attempts",
          "type": "integer[]",
          "primaryKey": false,
          "notNull": true,
          "default": "'{0,0,0}'"
        },
        "best_hit_ratio": {
          "name": "best_hit_ratio",
          "type": "real",
          "primaryKey": false,
          "notNull": true,
          "default": 0
        },
        "best_score": {
          "name": "best_score",
          "type": "integer",
          "primaryKey": false,
          "notNull": true,
          "default": 0
        }
      },
      "indexes": {},
      "foreignKeys": {},
      "compositePrimaryKeys": {},
      "uniqueConstraints": {},
      "policies": {},
      "checkConstraints": {},
      "isRLSEnabled": false
    },
    "public.user_game_play_counts": {
      "name": "user_game_play_counts",
      "schema": "",
      "columns": {
        "user_id": {
          "name": "user_id",
          "type": "uuid",
          "primaryKey": false,
          "notNull": true
        },
        "game_slug": {
          "name": "game_slug",
          "type": "varchar(64)",
          "primaryKey": false,
          "notNull": true
        },
        "play_count": {
          "name": "play_count",
          "type": "integer",
          "primaryKey": false,
          "notNull": true,
          "default": 0
        }
      },
      "indexes": {},
      "foreignKeys": {},
      "compositePrimaryKeys": {
        "user_game_play_counts_user_id_game_slug_pk": {
          "name": "user_game_play_counts_user_id_game_slug_pk",
          "columns": [
            "user_id",
            "game_slug"
          ]
        }
      },
      "uniqueConstraints": {},
      "policies": {},
      "checkConstraints": {},
      "isRLSEnabled": false
    },
    "public.user_preferences": {
      "name": "user_preferences",
      "schema": "",
      "columns": {
        "user_id": {
          "name": "user_id",
          "type": "uuid",
          "primaryKey": true,
          "notNull": true
        },
        "display_name": {
          "name": "display_name",
          "type": "varchar(20)",
          "primaryKey": false,
          "notNull": false
        },
        "updated_at": {
          "name": "updated_at",
          "type": "timestamp with time zone",
          "primaryKey": false,
          "notNull": true,
          "default": "now()"
        }
      },
      "indexes": {},
      "foreignKeys": {},
      "compositePrimaryKeys": {},
      "uniqueConstraints": {},
      "policies": {},
      "checkConstraints": {},
      "isRLSEnabled": false
    }
  },
  "enums": {},
  "schemas": {},
  "sequences": {},
  "roles": {},
  "policies": {},
  "views": {},
  "_meta": {
    "columns": {},
    "schemas": {},
    "tables": {}
  }
}